{
    "@context": "/contexts/DeckUserList",
    "@id": "/deck_user_lists/01JM5539HMGADJKSNJYWKMZN09",
    "@type": "DeckUserList",
    "name": "KojoFuseau",
    "user": {
        "@id": "/users/01HM9QZP4ZGTWVSC6RM25FHK8H",
        "@type": "User",
        "id": "01HM9QZP4ZGTWVSC6RM25FHK8H"
    },
    "faction": {
        "@id": "/factions/BR",
        "@type": "Faction",
        "reference": "BR",
        "color": "#c32637",
        "id": "01GE7AC9WY6PK56RADXXD6P1T4",
        "name": "Bravos"
    },
    "alterator": {
        "@id": "/cards/ALT_CORE_B_BR_01_C",
        "@type": "Card",
        "cardType": {
            "@id": "/card_types/01GE7AC9WGQTNRP28T63FH8TZD",
            "@type": "CardType",
            "reference": "HERO",
            "id": "01GE7AC9WGQTNRP28T63FH8TZD",
            "name": "Héros"
        },
        "rarity": {
            "@id": "/rarities/COMMON",
            "@type": "Rarity",
            "reference": "COMMON",
            "name": "Commun"
        },
        "imagePath": "https://altered-prod-eu.s3.amazonaws.com/Art/CORE/CARDS/ALT_CORE_B_BR_01/JPG/fr_FR/b04bcfd0de9b98a2ad045213ad940efb.jpg",
        "inMyCollection": 0,
        "assets": {
            "WEB": [
                "https://altered-prod-eu.s3.amazonaws.com/Art/CORE/CARDS/ALT_CORE_B_BR_01/ALT_CORE_B_BR_01_C_WEB.jpg"
            ],
            "HERO_WIDE": [
                "https://altered-prod-eu.s3.amazonaws.com/Art/CORE/CARDS/ALT_CORE_B_BR_01/ALT_CORE_B_BR_01_C_HERO_WIDE.jpg"
            ],
            "HERO_THUMB": [
                "https://altered-prod-eu.s3.amazonaws.com/Art/CORE/CARDS/ALT_CORE_B_BR_01/ALT_CORE_B_BR_01_C_HERO_THUMB.jpg"
            ]
        },
        "reference": "ALT_CORE_B_BR_01_C",
        "id": "01HKAFJNMQBWA7WHAW59M2AEKN",
        "familyReference": "BR_01_C",
        "mainFaction": {
            "@id": "/factions/BR",
            "@type": "Faction",
            "reference": "BR",
            "color": "#c32637",
            "id": "01GE7AC9WY6PK56RADXXD6P1T4",
            "name": "Bravos"
        },
        "name": "Kojo & Booda",
        "elements": {
            "MAIN_COST": "0",
            "RECALL_COST": "0",
            "PERMANENT": "2",
            "RESERVE": "2",
            "MAIN_EFFECT": "À Midi — Si vous êtes le premier joueur, créez un jeton Compagnon [2/2/2 Booda] dans votre Expédition Compagnon."
        },
        "siblingReference": "BR_01"
    },
    "gameType": {
        "@id": "/game_types/01GDNGQY64G6NRWBZ7PYP0Z3E3",
        "@type": "GameType",
        "reference": "CONSTRUCTED",
        "name": "Construit"
    },
    "public": false,
    "cardQuantity": 39,
    "deckLegality": {
        "@type": "DeckLegality",
        "@id": "/.well-known/genid/48395d15dbc2eb14e593",
        "resume": {
            "nbRare": true,
            "isOwned": true,
            "nbUnique": true,
            "isSameFaction": true,
            "nbFamily": true,
            "nbHero": true,
            "nbCards": true,
            "isSuspended": true,
            "globalValidity": true,
            "errorFamily": []
        }
    },
    "deckCardsByType": {
        "@type": "DeckCard",
        "@id": "/.well-known/genid/8188e8675bba2c51ba9a",
        "character": {
            "@type": "DeckCards",
            "@id": "/.well-known/genid/dedc394be6c4e1fb7f64",
            "deckUserListCard": [
                {
                    "@type": "DeckUserListCard",
                    "@id": "/.well-known/genid/2ba4cc623652646470da",
                    "quantity": 3,
                    "card": {
                        "@id": "/cards/ALT_COREKS_B_BR_06_R1",
                        "@type": "Card",
                        "cardType": {
                            "@id": "/card_types/01H19NWA92A4ERAC4ATMSZNASS",
                            "@type": "CardType",
                            "reference": "CHARACTER",
                            "id": "01H19NWA92A4ERAC4ATMSZNASS",
                            "name": "Personnage"
                        },
                        "rarity": {
                            "@id": "/rarities/RARE",
                            "@type": "Rarity",
                            "reference": "RARE",
                            "name": "Rare"
                        },
                        "imagePath": "https://altered-prod-eu.s3.amazonaws.com/Art/COREKS/CARDS/ALT_CORE_B_BR_06/JPG/fr_FR/74fdbfa44942d754849a710f83d1447d.jpg",
                        "inMyCollection": 0,
                        "assets": {
                            "WEB": [
                                "https://altered-prod-eu.s3.amazonaws.com/Art/CORE/CARDS/ALT_CORE_B_BR_06/ALT_CORE_B_BR_06_C_WEB.jpg",
                                "https://altered-prod-eu.s3.amazonaws.com/Art/CORE/CARDS/ALT_CORE_B_BR_06/ALT_CORE_B_BR_06_R_WEB.jpg",
                                "https://altered-prod-eu.s3.amazonaws.com/Art/CORE/CARDS/ALT_CORE_B_BR_06/ALT_CORE_B_BR_06_U_WEB.jpg"
                            ]
                        },
                        "reference": "ALT_COREKS_B_BR_06_R1",
                        "id": "01HN5TXR6ZEA7EH4457RX0JVR3",
                        "familyReference": "BR_06_R1",
                        "mainFaction": {
                            "@id": "/factions/BR",
                            "@type": "Faction",
                            "reference": "BR",
                            "color": "#c32637",
                            "id": "01GE7AC9WY6PK56RADXXD6P1T4",
                            "name": "Bravos"
                        },
                        "name": "Petit Djinn",
                        "elements": {
                            "MAIN_COST": "#1#",
                            "RECALL_COST": "#2#",
                            "OCEAN_POWER": "0",
                            "MOUNTAIN_POWER": "#2#",
                            "FOREST_POWER": "0",
                            "MAIN_EFFECT": "Si je devais quitter la zone d'Expédition en étant [[Boosté]], mettez-moi dans la zone de Mana de mon propriétaire à la place (en tant qu'Orbe de Mana épuisé).  {R} Je gagne 1 boost."
                        },
                        "siblingReference": "BR_06"
                    },
                    "id": "01JM5572EKFYMTY2X06Q39VXJ9"
                },
                {
                    "@type": "DeckUserListCard",
                    "@id": "/.well-known/genid/1da5fa6fee3e393520f4",
                    "quantity": 3,
                    "card": {
                        "@id": "/cards/ALT_ALIZE_B_BR_32_C",
                        "@type": "Card",
                        "cardType": {
                            "@id": "/card_types/01H19NWA92A4ERAC4ATMSZNASS",
                            "@type": "CardType",
                            "reference": "CHARACTER",
                            "id": "01H19NWA92A4ERAC4ATMSZNASS",
                            "name": "Personnage"
                        },
                        "rarity": {
                            "@id": "/rarities/COMMON",
                            "@type": "Rarity",
                            "reference": "COMMON",
                            "name": "Commun"
                        },
                        "imagePath": "https://altered-prod-eu.s3.amazonaws.com/Art/ALIZE/CARDS/ALT_ALIZE_B_BR_32/JPG/fr_FR/9a92ece96e74fcb3eab326d5e1e07a14.jpg",
                        "inMyCollection": 0,
                        "assets": {
                            "WEB": [
                                "https://altered-prod-eu.s3.amazonaws.com/Art/ALIZE/CARDS/ALT_ALIZE_B_BR_32/WEB_ecd22757d73477fd48b6bcc15e233f6d",
                                "https://altered-prod-eu.s3.amazonaws.com/Art/ALIZE/CARDS/ALT_ALIZE_B_BR_32/WEB_009a5ebbc48a0c9e221efbfeadd4a138",
                                "https://altered-prod-eu.s3.amazonaws.com/Art/ALIZE/CARDS/ALT_ALIZE_B_BR_32/WEB_0a6b07195d27235c0c876f928511c6f6"
                            ]
                        },
                        "reference": "ALT_ALIZE_B_BR_32_C",
                        "id": "01J1Q4P4S0NB0MZ5JKYA2527DN",
                        "familyReference": "BR_32_C",
                        "mainFaction": {
                            "@id": "/factions/BR",
                            "@type": "Faction",
                            "reference": "BR",
                            "color": "#c32637",
                            "id": "01GE7AC9WY6PK56RADXXD6P1T4",
                            "name": "Bravos"
                        },
                        "name": "Lapin Ardent",
                        "elements": {
                            "MAIN_COST": "1",
                            "RECALL_COST": "1",
                            "OCEAN_POWER": "0",
                            "FOREST_POWER": "1",
                            "MOUNTAIN_POWER": "1",
                            "MAIN_EFFECT": "{H} Vous pouvez me faire gagner [[Fugace]]. Si vous le faites, un autre Personnage ciblé gagne 1 boost."
                        },
                        "siblingReference": "BR_32"
                    },
                    "id": "01JM55HE7XT18TDKTEYDN3DNMV"
                },
                {
                    "@type": "DeckUserListCard",
                    "@id": "/.well-known/genid/9bdfedaca4df8aa9a512",
                    "quantity": 2,
                    "card": {
                        "@id": "/cards/ALT_ALIZE_B_BR_33_C",
                        "@type": "Card",
                        "cardType": {
                            "@id": "/card_types/01H19NWA92A4ERAC4ATMSZNASS",
                            "@type": "CardType",
                            "reference": "CHARACTER",
                            "id": "01H19NWA92A4ERAC4ATMSZNASS",
                            "name": "Personnage"
                        },
                        "rarity": {
                            "@id": "/rarities/COMMON",
                            "@type": "Rarity",
                            "reference": "COMMON",
                            "name": "Commun"
                        },
                        "imagePath": "https://altered-prod-eu.s3.amazonaws.com/Art/ALIZE/CARDS/ALT_ALIZE_B_BR_33/JPG/fr_FR/d1a1fadf76625388151cc2726a8d9248.jpg",
                        "inMyCollection": 0,
                        "assets": {
                            "WEB": [
                                "https://altered-prod-eu.s3.amazonaws.com/Art/ALIZE/CARDS/ALT_ALIZE_B_BR_33/WEB_7a3b8b578540a11a0424b8db1e7b3ca1",
                                "https://altered-prod-eu.s3.amazonaws.com/Art/ALIZE/CARDS/ALT_ALIZE_B_BR_33/WEB_4826f87809b72319b9d4debeded29cb8",
                                "https://altered-prod-eu.s3.amazonaws.com/Art/ALIZE/CARDS/ALT_ALIZE_B_BR_33/WEB_ae0e6fdee2145e21bee716f650ff0b14"
                            ]
                        },
                        "reference": "ALT_ALIZE_B_BR_33_C",
                        "id": "01J1Q4P4S0NB0MZ5JKYA2527DY",
                        "familyReference": "BR_33_C",
                        "mainFaction": {
                            "@id": "/factions/BR",
                            "@type": "Faction",
                            "reference": "BR",
                            "color": "#c32637",
                            "id": "01GE7AC9WY6PK56RADXXD6P1T4",
                            "name": "Bravos"
                        },
                        "name": "Skadi",
                        "elements": {
                            "MAIN_COST": "2",
                            "RECALL_COST": "3",
                            "OCEAN_POWER": "2",
                            "FOREST_POWER": "2",
                            "MOUNTAIN_POWER": "3",
                            "MAIN_EFFECT": "{R} Vous pouvez épuiser ({T}) une carte ciblée en Réserve. (Une carte épuisée ne peut pas être jouée et n'a pas de capacité de Soutien.)"
                        },
                        "siblingReference": "BR_33"
                    },
                    "id": "01JMAJDR7ZKVQ77EF60P4G2MP5"
                },
                {
                    "@type": "DeckUserListCard",
                    "@id": "/.well-known/genid/6de76d3c4403496194bb",
                    "quantity": 3,
                    "card": {
                        "@id": "/cards/ALT_ALIZE_B_BR_34_C",
                        "@type": "Card",
                        "cardType": {
                            "@id": "/card_types/01H19NWA92A4ERAC4ATMSZNASS",
                            "@type": "CardType",
                            "reference": "CHARACTER",
                            "id": "01H19NWA92A4ERAC4ATMSZNASS",
                            "name": "Personnage"
                        },
                        "rarity": {
                            "@id": "/rarities/COMMON",
                            "@type": "Rarity",
                            "reference": "COMMON",
                            "name": "Commun"
                        },
                        "imagePath": "https://altered-prod-eu.s3.amazonaws.com/Art/ALIZE/CARDS/ALT_ALIZE_B_BR_34/JPG/fr_FR/a54f4cae4c24866b00fe464894b8f700.jpg",
                        "inMyCollection": 0,
                        "assets": {
                            "WEB": [
                                "https://altered-prod-eu.s3.amazonaws.com/Art/ALIZE/CARDS/ALT_ALIZE_B_BR_34/WEB_d865360de938c343bfd21be56818dca5",
                                "https://altered-prod-eu.s3.amazonaws.com/Art/ALIZE/CARDS/ALT_ALIZE_B_BR_34/WEB_4101215de65acd5aecd43196530dc333",
                                "https://altered-prod-eu.s3.amazonaws.com/Art/ALIZE/CARDS/ALT_ALIZE_B_BR_34/WEB_d6bc73bb04247722faba819da0ae4fe6"
                            ]
                        },
                        "reference": "ALT_ALIZE_B_BR_34_C",
                        "id": "01J1Q4P4S1E6BR3CRG4TVW2HED",
                        "familyReference": "BR_34_C",
                        "mainFaction": {
                            "@id": "/factions/BR",
                            "@type": "Faction",
                            "reference": "BR",
                            "color": "#c32637",
                            "id": "01GE7AC9WY6PK56RADXXD6P1T4",
                            "name": "Bravos"
                        },
                        "name": "Seiringar de Havre",
                        "elements": {
                            "MAIN_COST": "2",
                            "RECALL_COST": "2",
                            "OCEAN_POWER": "1",
                            "FOREST_POWER": "3",
                            "MOUNTAIN_POWER": "1",
                            "MAIN_EFFECT": "Lorsque je quitte la zone d'Expédition, si j'étais [[Fugace]] — Piochez une carte."
                        },
                        "siblingReference": "BR_34"
                    },
                    "id": "01JM553TY5DB73QRNHNHA139PW"
                },
                {
                    "@type": "DeckUserListCard",
                    "@id": "/.well-known/genid/6c63b2c65f71c4b44a48",
                    "quantity": 3,
                    "card": {
                        "@id": "/cards/ALT_ALIZE_B_BR_35_C",
                        "@type": "Card",
                        "cardType": {
                            "@id": "/card_types/01H19NWA92A4ERAC4ATMSZNASS",
                            "@type": "CardType",
                            "reference": "CHARACTER",
                            "id": "01H19NWA92A4ERAC4ATMSZNASS",
                            "name": "Personnage"
                        },
                        "rarity": {
                            "@id": "/rarities/COMMON",
                            "@type": "Rarity",
                            "reference": "COMMON",
                            "name": "Commun"
                        },
                        "imagePath": "https://altered-prod-eu.s3.amazonaws.com/Art/ALIZE/CARDS/ALT_ALIZE_B_BR_35/JPG/fr_FR/43df0dcf02486349006962ed9f0404da.jpg",
                        "inMyCollection": 0,
                        "assets": {
                            "WEB": [
                                "https://altered-prod-eu.s3.amazonaws.com/Art/ALIZE/CARDS/ALT_ALIZE_B_BR_35/WEB_aaa6686002e7acd962fbd6ba1553b83e",
                                "https://altered-prod-eu.s3.amazonaws.com/Art/ALIZE/CARDS/ALT_ALIZE_B_BR_35/WEB_e17e17996b43565b3ff9397cc1defa39",
                                "https://altered-prod-eu.s3.amazonaws.com/Art/ALIZE/CARDS/ALT_ALIZE_B_BR_35/WEB_5ec0e03b5a1389a867d4128c6c1b0f40"
                            ]
                        },
                        "reference": "ALT_ALIZE_B_BR_35_C",
                        "id": "01J1Q4P4S1E6BR3CRG4TVW2HEP",
                        "familyReference": "BR_35_C",
                        "mainFaction": {
                            "@id": "/factions/BR",
                            "@type": "Faction",
                            "reference": "BR",
                            "color": "#c32637",
                            "id": "01GE7AC9WY6PK56RADXXD6P1T4",
                            "name": "Bravos"
                        },
                        "name": "Déblayeur Bravos",
                        "elements": {
                            "MAIN_COST": "2",
                            "RECALL_COST": "3",
                            "OCEAN_POWER": "2",
                            "FOREST_POWER": "2",
                            "MOUNTAIN_POWER": "2",
                            "MAIN_EFFECT": "{J} Si vous contrôlez un Personnage [[Fugace]], je gagne 1 boost."
                        },
                        "siblingReference": "BR_35"
                    },
                    "id": "01JM5738VNNB4ZGVRM7GK71WCP"
                },
                {
                    "@type": "DeckUserListCard",
                    "@id": "/.well-known/genid/6a4280a5a05fcb85a768",
                    "quantity": 2,
                    "card": {
                        "@id": "/cards/ALT_COREKS_B_BR_08_C",
                        "@type": "Card",
                        "cardType": {
                            "@id": "/card_types/01H19NWA92A4ERAC4ATMSZNASS",
                            "@type": "CardType",
                            "reference": "CHARACTER",
                            "id": "01H19NWA92A4ERAC4ATMSZNASS",
                            "name": "Personnage"
                        },
                        "rarity": {
                            "@id": "/rarities/COMMON",
                            "@type": "Rarity",
                            "reference": "COMMON",
                            "name": "Commun"
                        },
                        "imagePath": "https://altered-prod-eu.s3.amazonaws.com/Art/COREKS/CARDS/ALT_CORE_B_BR_08/JPG/fr_FR/aa044366aa92fdf93a8fe6cc79678e7d.jpg",
                        "inMyCollection": 0,
                        "assets": {
                            "WEB": [
                                "https://altered-prod-eu.s3.amazonaws.com/Art/CORE/CARDS/ALT_CORE_B_BR_08/ALT_CORE_B_BR_08_C_WEB.jpg",
                                "https://altered-prod-eu.s3.amazonaws.com/Art/CORE/CARDS/ALT_CORE_B_BR_08/ALT_CORE_B_BR_08_R_WEB.jpg",
                                "https://altered-prod-eu.s3.amazonaws.com/Art/CORE/CARDS/ALT_CORE_B_BR_08/ALT_CORE_B_BR_08_U_WEB.jpg"
                            ]
                        },
                        "reference": "ALT_COREKS_B_BR_08_C",
                        "id": "01HN5TXR76AH3YMZDE32Q4PCZA",
                        "familyReference": "BR_08_C",
                        "mainFaction": {
                            "@id": "/factions/BR",
                            "@type": "Faction",
                            "reference": "BR",
                            "color": "#c32637",
                            "id": "01GE7AC9WY6PK56RADXXD6P1T4",
                            "name": "Bravos"
                        },
                        "name": "Pionnière Bravos",
                        "elements": {
                            "MAIN_COST": "2",
                            "RECALL_COST": "2",
                            "OCEAN_POWER": "3",
                            "MOUNTAIN_POWER": "3",
                            "FOREST_POWER": "0"
                        },
                        "siblingReference": "BR_08"
                    },
                    "id": "01JM557CBZJTN4KRRT4P7EVJDB"
                },
                {
                    "@type": "DeckUserListCard",
                    "@id": "/.well-known/genid/1f263918b843c7ebbcd5",
                    "quantity": 1,
                    "card": {
                        "@id": "/cards/ALT_COREKS_B_BR_17_U_1328",
                        "@type": "Card",
                        "cardType": {
                            "@id": "/card_types/01H19NWA92A4ERAC4ATMSZNASS",
                            "@type": "CardType",
                            "reference": "CHARACTER",
                            "id": "01H19NWA92A4ERAC4ATMSZNASS",
                            "name": "Personnage"
                        },
                        "rarity": {
                            "@id": "/rarities/UNIQUE",
                            "@type": "Rarity",
                            "reference": "UNIQUE",
                            "name": "Unique"
                        },
                        "imagePath": "https://altered-prod-eu.s3.amazonaws.com/Art/COREKS/CARDS/ALT_CORE_B_BR_17/UNIQUE/JPG/fr_FR/6a5488a27b8fecc305a9252ae9313cad.jpg",
                        "inMyCollection": 0,
                        "assets": {
                            "WEB": [
                                "https://altered-prod-eu.s3.amazonaws.com/Art/CORE/CARDS/ALT_CORE_B_BR_17/ALT_CORE_B_BR_17_C_WEB.jpg",
                                "https://altered-prod-eu.s3.amazonaws.com/Art/CORE/CARDS/ALT_CORE_B_BR_17/ALT_CORE_B_BR_17_R_WEB.jpg",
                                "https://altered-prod-eu.s3.amazonaws.com/Art/CORE/CARDS/ALT_CORE_B_BR_17/ALT_CORE_B_BR_17_U_WEB.jpg"
                            ]
                        },
                        "reference": "ALT_COREKS_B_BR_17_U_1328",
                        "id": "4SZ0GNB67B8V2SV93QXB4B45FB",
                        "familyReference": "BR_17_U_1328",
                        "mainFaction": {
                            "@id": "/factions/BR",
                            "@type": "Faction",
                            "reference": "BR",
                            "color": "#c32637",
                            "id": "01GE7AC9WY6PK56RADXXD6P1T4",
                            "name": "Bravos"
                        },
                        "name": "Guerrière de Havre",
                        "elements": {
                            "MAIN_COST": "2",
                            "RECALL_COST": "2",
                            "MOUNTAIN_POWER": "2",
                            "OCEAN_POWER": "1",
                            "FOREST_POWER": "2",
                            "MAIN_EFFECT": "{J} Vous pouvez payer {1}. Si vous le faites : Piochez une carte."
                        },
                        "siblingReference": "BR_17"
                    },
                    "id": "01JMN0TWRF9YMZVM9B8XC7Y12N"
                },
                {
                    "@type": "DeckUserListCard",
                    "@id": "/.well-known/genid/872d8511e79eaee82c91",
                    "quantity": 2,
                    "card": {
                        "@id": "/cards/ALT_COREKS_B_BR_15_C",
                        "@type": "Card",
                        "cardType": {
                            "@id": "/card_types/01H19NWA92A4ERAC4ATMSZNASS",
                            "@type": "CardType",
                            "reference": "CHARACTER",
                            "id": "01H19NWA92A4ERAC4ATMSZNASS",
                            "name": "Personnage"
                        },
                        "rarity": {
                            "@id": "/rarities/COMMON",
                            "@type": "Rarity",
                            "reference": "COMMON",
                            "name": "Commun"
                        },
                        "imagePath": "https://altered-prod-eu.s3.amazonaws.com/Art/COREKS/CARDS/ALT_CORE_B_BR_15/JPG/fr_FR/68e30b1ee723aa7dbead18865e4fe58a.jpg",
                        "inMyCollection": 0,
                        "assets": {
                            "WEB": [
                                "https://altered-prod-eu.s3.amazonaws.com/Art/CORE/CARDS/ALT_CORE_B_BR_15/ALT_CORE_B_BR_15_C_WEB.jpg",
                                "https://altered-prod-eu.s3.amazonaws.com/Art/CORE/CARDS/ALT_CORE_B_BR_15/ALT_CORE_B_BR_15_R_WEB.jpg",
                                "https://altered-prod-eu.s3.amazonaws.com/Art/CORE/CARDS/ALT_CORE_B_BR_15/ALT_CORE_B_BR_15_U_WEB.jpg"
                            ]
                        },
                        "reference": "ALT_COREKS_B_BR_15_C",
                        "id": "01HN5TXR813DNNH4ZETSM5AZGK",
                        "familyReference": "BR_15_C",
                        "mainFaction": {
                            "@id": "/factions/BR",
                            "@type": "Faction",
                            "reference": "BR",
                            "color": "#c32637",
                            "id": "01GE7AC9WY6PK56RADXXD6P1T4",
                            "name": "Bravos"
                        },
                        "name": "Videuse Bravos",
                        "elements": {
                            "MAIN_COST": "3",
                            "RECALL_COST": "3",
                            "OCEAN_POWER": "2",
                            "MOUNTAIN_POWER": "2",
                            "FOREST_POWER": "2",
                            "MAIN_EFFECT": "{H} [Sabotez]. (Défaussez jusqu'à une carte d'une Réserve.)  {R} Je gagne 1 boost[]. (Un boost est un compteur +1/+1/+1. Retirez-le lorsqu'il quitte la zone d'Expédition.)"
                        },
                        "siblingReference": "BR_15"
                    },
                    "id": "01JM557RH4TN4AGHF49N468BE5"
                },
                {
                    "@type": "DeckUserListCard",
                    "@id": "/.well-known/genid/12f0c2d006814c3d8df1",
                    "quantity": 1,
                    "card": {
                        "@id": "/cards/ALT_COREKS_B_LY_09_U_1373",
                        "@type": "Card",
                        "cardType": {
                            "@id": "/card_types/01H19NWA92A4ERAC4ATMSZNASS",
                            "@type": "CardType",
                            "reference": "CHARACTER",
                            "id": "01H19NWA92A4ERAC4ATMSZNASS",
                            "name": "Personnage"
                        },
                        "rarity": {
                            "@id": "/rarities/UNIQUE",
                            "@type": "Rarity",
                            "reference": "UNIQUE",
                            "name": "Unique"
                        },
                        "imagePath": "https://altered-prod-eu.s3.amazonaws.com/Art/COREKS/CARDS/ALT_COREKS_B_LY_09/UNIQUE/JPG/fr_FR/c4da96795bedb3c98a6e86705343a154.jpg",
                        "inMyCollection": 0,
                        "assets": {
                            "WEB": [
                                "https://altered-prod-eu.s3.amazonaws.com/Art/COREKS/CARDS/ALT_COREKS_B_LY_09/WEB_73b3fddf0382681b4fa26cf39ced7f8c",
                                "https://altered-prod-eu.s3.amazonaws.com/Art/COREKS/CARDS/ALT_COREKS_B_LY_09/WEB_6211639ee94ede65ab69bc4b7a1ffca2",
                                "https://altered-prod-eu.s3.amazonaws.com/Art/COREKS/CARDS/ALT_COREKS_B_LY_09/WEB_f99ce23a9fc65e30cda3fe73527d9792"
                            ]
                        },
                        "reference": "ALT_COREKS_B_LY_09_U_1373",
                        "id": "3FJCP7DC8J8XMAV7RDNCBC89DB",
                        "familyReference": "LY_09_U_1373",
                        "mainFaction": {
                            "@id": "/factions/BR",
                            "@type": "Faction",
                            "reference": "BR",
                            "color": "#c32637",
                            "id": "01GE7AC9WY6PK56RADXXD6P1T4",
                            "name": "Bravos"
                        },
                        "name": "Tanuki",
                        "elements": {
                            "MAIN_COST": "3",
                            "RECALL_COST": "4",
                            "MOUNTAIN_POWER": "3",
                            "OCEAN_POWER": "0",
                            "FOREST_POWER": "4",
                            "MAIN_EFFECT": "{J} []Piochez une carte.  {R} Vous pouvez mettre une carte de votre main en Réserve. Si vous le faites : [Sabotez].",
                            "ECHO_EFFECT": "{D} : []Vous pouvez faire perdre [[Fugace]] à un Personnage ciblé autre que moi."
                        },
                        "siblingReference": "LY_09"
                    },
                    "id": "01JM55590AXSVSWQFZMS8YV6AB"
                },
                {
                    "@type": "DeckUserListCard",
                    "@id": "/.well-known/genid/13ddb8f4697bfcd0976a",
                    "quantity": 2,
                    "card": {
                        "@id": "/cards/ALT_COREKS_B_BR_19_R1",
                        "@type": "Card",
                        "cardType": {
                            "@id": "/card_types/01H19NWA92A4ERAC4ATMSZNASS",
                            "@type": "CardType",
                            "reference": "CHARACTER",
                            "id": "01H19NWA92A4ERAC4ATMSZNASS",
                            "name": "Personnage"
                        },
                        "rarity": {
                            "@id": "/rarities/RARE",
                            "@type": "Rarity",
                            "reference": "RARE",
                            "name": "Rare"
                        },
                        "imagePath": "https://altered-prod-eu.s3.amazonaws.com/Art/COREKS/CARDS/ALT_CORE_B_BR_19/JPG/fr_FR/dddc7346b15ad1bb51017c4002b90555.jpg",
                        "inMyCollection": 0,
                        "assets": {
                            "WEB": [
                                "https://altered-prod-eu.s3.amazonaws.com/Art/CORE/CARDS/ALT_CORE_B_BR_19/ALT_CORE_B_BR_19_C_WEB.jpg",
                                "https://altered-prod-eu.s3.amazonaws.com/Art/CORE/CARDS/ALT_CORE_B_BR_19/ALT_CORE_B_BR_19_R_WEB.jpg",
                                "https://altered-prod-eu.s3.amazonaws.com/Art/CORE/CARDS/ALT_CORE_B_BR_19/ALT_CORE_B_BR_19_U_WEB.jpg"
                            ]
                        },
                        "reference": "ALT_COREKS_B_BR_19_R1",
                        "id": "01HN5TXR8J6K1006FQX4R0M760",
                        "familyReference": "BR_19_R1",
                        "mainFaction": {
                            "@id": "/factions/BR",
                            "@type": "Faction",
                            "reference": "BR",
                            "color": "#c32637",
                            "id": "01GE7AC9WY6PK56RADXXD6P1T4",
                            "name": "Bravos"
                        },
                        "name": "Puissant Djinn",
                        "elements": {
                            "MAIN_COST": "4",
                            "RECALL_COST": "3",
                            "OCEAN_POWER": "0",
                            "MOUNTAIN_POWER": "4",
                            "FOREST_POWER": "4",
                            "MAIN_EFFECT": "Si je devais quitter la zone d’Expédition, vous pouvez me mettre dans la zone de Mana de mon propriétaire à la place (en tant qu'Orbe de Mana épuisé).  #Si vous ne le faites pas, piochez une carte.#"
                        },
                        "siblingReference": "BR_19"
                    },
                    "id": "01JM554P25AJKAC0G8P4NH3ZWV"
                },
                {
                    "@type": "DeckUserListCard",
                    "@id": "/.well-known/genid/863a72b2bd7d63263d78",
                    "quantity": 2,
                    "card": {
                        "@id": "/cards/ALT_CORE_B_MU_18_R2",
                        "@type": "Card",
                        "cardType": {
                            "@id": "/card_types/01H19NWA92A4ERAC4ATMSZNASS",
                            "@type": "CardType",
                            "reference": "CHARACTER",
                            "id": "01H19NWA92A4ERAC4ATMSZNASS",
                            "name": "Personnage"
                        },
                        "rarity": {
                            "@id": "/rarities/RARE",
                            "@type": "Rarity",
                            "reference": "RARE",
                            "name": "Rare"
                        },
                        "imagePath": "https://altered-prod-eu.s3.amazonaws.com/Art/CORE/CARDS/ALT_CORE_B_MU_18/JPG/fr_FR/e1120cd67dbbc78d157c5c5c43fc5e68.jpg",
                        "inMyCollection": 0,
                        "assets": {
                            "WEB": [
                                "https://altered-prod-eu.s3.amazonaws.com/Art/CORE/CARDS/ALT_CORE_B_MU_18/ALT_CORE_B_MU_18_C_WEB.jpg",
                                "https://altered-prod-eu.s3.amazonaws.com/Art/CORE/CARDS/ALT_CORE_B_MU_18/ALT_CORE_B_MU_18_R_WEB.jpg",
                                "https://altered-prod-eu.s3.amazonaws.com/Art/CORE/CARDS/ALT_CORE_B_MU_18/ALT_CORE_B_MU_18_U_WEB.jpg"
                            ]
                        },
                        "reference": "ALT_CORE_B_MU_18_R2",
                        "id": "01HKAFJP7X6BSZWDZ4X70D5QDZ",
                        "familyReference": "MU_18_R2",
                        "mainFaction": {
                            "@id": "/factions/BR",
                            "@type": "Faction",
                            "reference": "BR",
                            "color": "#c32637",
                            "id": "01GE7AC9WY6PK56RADXXD6P1T4",
                            "name": "Bravos"
                        },
                        "name": "Parvati",
                        "elements": {
                            "MAIN_COST": "4",
                            "RECALL_COST": "#3#",
                            "OCEAN_POWER": "3",
                            "MOUNTAIN_POWER": "0",
                            "FOREST_POWER": "3",
                            "MAIN_EFFECT": "#{J}# Un Personnage ciblé gagne [[Ancré]]. (Au Repos, il ne va pas en Réserve et il perd Ancré.)"
                        },
                        "siblingReference": "MU_18"
                    },
                    "id": "01JMN8KEWZMX2ZARKKXXVQ7V3E"
                },
                {
                    "@type": "DeckUserListCard",
                    "@id": "/.well-known/genid/5db905a0bc9cb413e7fd",
                    "quantity": 1,
                    "card": {
                        "@id": "/cards/ALT_COREKS_B_LY_18_U_488",
                        "@type": "Card",
                        "cardType": {
                            "@id": "/card_types/01H19NWA92A4ERAC4ATMSZNASS",
                            "@type": "CardType",
                            "reference": "CHARACTER",
                            "id": "01H19NWA92A4ERAC4ATMSZNASS",
                            "name": "Personnage"
                        },
                        "rarity": {
                            "@id": "/rarities/UNIQUE",
                            "@type": "Rarity",
                            "reference": "UNIQUE",
                            "name": "Unique"
                        },
                        "imagePath": "https://altered-prod-eu.s3.amazonaws.com/Art/COREKS/CARDS/ALT_CORE_B_LY_18/UNIQUE/JPG/fr_FR/d269cee286a1dd21f8fd6d8ea152051c.jpg",
                        "inMyCollection": 0,
                        "assets": {
                            "WEB": [
                                "https://altered-prod-eu.s3.amazonaws.com/Art/CORE/CARDS/ALT_CORE_B_LY_18/ALT_CORE_B_LY_18_C_WEB.jpg",
                                "https://altered-prod-eu.s3.amazonaws.com/Art/CORE/CARDS/ALT_CORE_B_LY_18/ALT_CORE_B_LY_18_R_WEB.jpg",
                                "https://altered-prod-eu.s3.amazonaws.com/Art/CORE/CARDS/ALT_CORE_B_LY_18/ALT_CORE_B_LY_18_U_WEB.jpg"
                            ]
                        },
                        "reference": "ALT_COREKS_B_LY_18_U_488",
                        "id": "17Y01GM2YQ9MT9FX6YJ578MZ8P",
                        "familyReference": "LY_18_U_488",
                        "mainFaction": {
                            "@id": "/factions/BR",
                            "@type": "Faction",
                            "reference": "BR",
                            "color": "#c32637",
                            "id": "01GE7AC9WY6PK56RADXXD6P1T4",
                            "name": "Bravos"
                        },
                        "name": "Le Chapelier",
                        "elements": {
                            "MAIN_COST": "6",
                            "RECALL_COST": "6",
                            "MOUNTAIN_POWER": "4",
                            "OCEAN_POWER": "0",
                            "FOREST_POWER": "6",
                            "MAIN_EFFECT": "Au Crépuscule — []Mettez les deux premières cartes de votre deck dans votre zone de Mana (en tant qu'Orbes de Mana épuisés).",
                            "ECHO_EFFECT": "{D} : []Jusqu'à un Personnage ciblé de Coût de Main {3} ou moins autre que moi gagne [[Ancré]]."
                        },
                        "siblingReference": "LY_18"
                    },
                    "id": "01JM555EAQGJZC00S4Y7RDNJ7V"
                }
            ],
            "number": 25
        },
        "spell": {
            "@type": "DeckCards",
            "@id": "/.well-known/genid/812b6ef4dc17f19c192c",
            "deckUserListCard": [
                {
                    "@type": "DeckUserListCard",
                    "@id": "/.well-known/genid/ebc8d5cb9709edb773e8",
                    "quantity": 2,
                    "card": {
                        "@id": "/cards/ALT_COREKS_B_BR_29_R1",
                        "@type": "Card",
                        "cardType": {
                            "@id": "/card_types/01GE7AC9X35JXEQZJBBD6E4BKX",
                            "@type": "CardType",
                            "reference": "SPELL",
                            "id": "01GE7AC9X35JXEQZJBBD6E4BKX",
                            "name": "Sort"
                        },
                        "rarity": {
                            "@id": "/rarities/RARE",
                            "@type": "Rarity",
                            "reference": "RARE",
                            "name": "Rare"
                        },
                        "imagePath": "https://altered-prod-eu.s3.amazonaws.com/Art/COREKS/CARDS/ALT_CORE_B_BR_29/JPG/fr_FR/f291f725ac4c4e7648c18807321197cd.jpg",
                        "inMyCollection": 0,
                        "assets": {
                            "WEB": [
                                "https://altered-prod-eu.s3.amazonaws.com/Art/CORE/CARDS/ALT_CORE_B_BR_29/ALT_CORE_B_BR_29_C_WEB.jpg",
                                "https://altered-prod-eu.s3.amazonaws.com/Art/CORE/CARDS/ALT_CORE_B_BR_29/ALT_CORE_B_BR_29_R_WEB.jpg"
                            ]
                        },
                        "reference": "ALT_COREKS_B_BR_29_R1",
                        "id": "01HN5TXR9RZ90SFNTMS0CEVM1B",
                        "familyReference": "BR_29_R1",
                        "mainFaction": {
                            "@id": "/factions/BR",
                            "@type": "Faction",
                            "reference": "BR",
                            "color": "#c32637",
                            "id": "01GE7AC9WY6PK56RADXXD6P1T4",
                            "name": "Bravos"
                        },
                        "name": "Éruption de Mana",
                        "elements": {
                            "MAIN_COST": "#2#",
                            "RECALL_COST": "#2#",
                            "OCEAN_POWER": "",
                            "MOUNTAIN_POWER": "",
                            "FOREST_POWER": "",
                            "MAIN_EFFECT": "[[Fugace]]. (Envoyez-moi à la Défausse plutôt qu'en Réserve après résolution de mon effet.)  Défaussez un de vos Orbes de Mana. Si vous le faites, défaussez un Personnage ou Permanent ciblé."
                        },
                        "siblingReference": "BR_29"
                    },
                    "id": "01JM56CKP6V7WPS0BSPAC92TJG"
                },
                {
                    "@type": "DeckUserListCard",
                    "@id": "/.well-known/genid/ec57dd3dc1d17659c5f1",
                    "quantity": 3,
                    "card": {
                        "@id": "/cards/ALT_COREKS_B_BR_26_R1",
                        "@type": "Card",
                        "cardType": {
                            "@id": "/card_types/01GE7AC9X35JXEQZJBBD6E4BKX",
                            "@type": "CardType",
                            "reference": "SPELL",
                            "id": "01GE7AC9X35JXEQZJBBD6E4BKX",
                            "name": "Sort"
                        },
                        "rarity": {
                            "@id": "/rarities/RARE",
                            "@type": "Rarity",
                            "reference": "RARE",
                            "name": "Rare"
                        },
                        "imagePath": "https://altered-prod-eu.s3.amazonaws.com/Art/COREKS/CARDS/ALT_CORE_B_BR_26/JPG/fr_FR/0989bdb85beff181cb4911a4c62ebdbc.jpg",
                        "inMyCollection": 0,
                        "assets": {
                            "WEB": [
                                "https://altered-prod-eu.s3.amazonaws.com/Art/CORE/CARDS/ALT_CORE_B_BR_26/ALT_CORE_B_BR_26_R_WEB.jpg",
                                "https://altered-prod-eu.s3.amazonaws.com/Art/CORE/CARDS/ALT_CORE_B_BR_26/ALT_CORE_B_BR_26_U_WEB.jpg"
                            ]
                        },
                        "reference": "ALT_COREKS_B_BR_26_R1",
                        "id": "01HN5TXR9D3NYQBQZKGGMQTRCN",
                        "familyReference": "BR_26_R1",
                        "mainFaction": {
                            "@id": "/factions/BR",
                            "@type": "Faction",
                            "reference": "BR",
                            "color": "#c32637",
                            "id": "01GE7AC9WY6PK56RADXXD6P1T4",
                            "name": "Bravos"
                        },
                        "name": "Entraînement Physique",
                        "elements": {
                            "MAIN_COST": "#3#",
                            "RECALL_COST": "3",
                            "OCEAN_POWER": "",
                            "MOUNTAIN_POWER": "",
                            "FOREST_POWER": "",
                            "MAIN_EFFECT": "Un Personnage ciblé gagne 3 boosts[]. (Un boost est un compteur +1/+1/+1. Retirez-le lorsqu'il quitte la zone d'Expédition.)  #Piochez une carte.#"
                        },
                        "siblingReference": "BR_26"
                    },
                    "id": "01JM554V8R1V06BTA06ZXA83HK"
                },
                {
                    "@type": "DeckUserListCard",
                    "@id": "/.well-known/genid/2c06fba32b6dbfe74708",
                    "quantity": 1,
                    "card": {
                        "@id": "/cards/ALT_COREKS_B_BR_27_C",
                        "@type": "Card",
                        "cardType": {
                            "@id": "/card_types/01GE7AC9X35JXEQZJBBD6E4BKX",
                            "@type": "CardType",
                            "reference": "SPELL",
                            "id": "01GE7AC9X35JXEQZJBBD6E4BKX",
                            "name": "Sort"
                        },
                        "rarity": {
                            "@id": "/rarities/COMMON",
                            "@type": "Rarity",
                            "reference": "COMMON",
                            "name": "Commun"
                        },
                        "imagePath": "https://altered-prod-eu.s3.amazonaws.com/Art/COREKS/CARDS/ALT_CORE_B_BR_27/JPG/fr_FR/10647ea6e09abef38e11983a0d6e8285.jpg",
                        "inMyCollection": 0,
                        "assets": {
                            "WEB": [
                                "https://altered-prod-eu.s3.amazonaws.com/Art/CORE/CARDS/ALT_CORE_B_BR_27/WEB_3d492f8cb59e016efcc6ba6659ea94a6",
                                "https://altered-prod-eu.s3.amazonaws.com/Art/CORE/CARDS/ALT_CORE_B_BR_27/WEB_9fe8e4be6b446bc79fa67918291d9fc8"
                            ]
                        },
                        "reference": "ALT_COREKS_B_BR_27_C",
                        "id": "01HN5TXR9G0FEAGEWPMWHBVN1M",
                        "familyReference": "BR_27_C",
                        "mainFaction": {
                            "@id": "/factions/BR",
                            "@type": "Faction",
                            "reference": "BR",
                            "color": "#c32637",
                            "id": "01GE7AC9WY6PK56RADXXD6P1T4",
                            "name": "Bravos"
                        },
                        "name": "Canalisation de Mana",
                        "elements": {
                            "MAIN_COST": "2",
                            "RECALL_COST": "2",
                            "MAIN_EFFECT": "[[Fugace]]. (Envoyez-moi à la Défausse plutôt qu'en Réserve après résolution de mon effet.)  Mettez la première carte de votre deck dans votre zone de Mana (en tant qu'Orbe de Mana épuisé)."
                        },
                        "siblingReference": "BR_27"
                    },
                    "id": "01JMMTGWNQP549ABVY9TC0WS81"
                },
                {
                    "@type": "DeckUserListCard",
                    "@id": "/.well-known/genid/a42f87af05cf2abdb0b5",
                    "quantity": 3,
                    "card": {
                        "@id": "/cards/ALT_COREKS_B_BR_28_C",
                        "@type": "Card",
                        "cardType": {
                            "@id": "/card_types/01GE7AC9X35JXEQZJBBD6E4BKX",
                            "@type": "CardType",
                            "reference": "SPELL",
                            "id": "01GE7AC9X35JXEQZJBBD6E4BKX",
                            "name": "Sort"
                        },
                        "rarity": {
                            "@id": "/rarities/COMMON",
                            "@type": "Rarity",
                            "reference": "COMMON",
                            "name": "Commun"
                        },
                        "imagePath": "https://altered-prod-eu.s3.amazonaws.com/Art/COREKS/CARDS/ALT_CORE_B_BR_28/JPG/fr_FR/ec70d7429efac23a0ef9907597f89057.jpg",
                        "inMyCollection": 0,
                        "assets": {
                            "WEB": [
                                "https://altered-prod-eu.s3.amazonaws.com/Art/CORE/CARDS/ALT_CORE_B_BR_28/ALT_CORE_B_BR_28_C_WEB.jpg",
                                "https://altered-prod-eu.s3.amazonaws.com/Art/CORE/CARDS/ALT_CORE_B_BR_28/ALT_CORE_B_BR_28_R_WEB.jpg"
                            ]
                        },
                        "reference": "ALT_COREKS_B_BR_28_C",
                        "id": "01HN5TXR9K42ZKEQH5A4M9041R",
                        "familyReference": "BR_28_C",
                        "mainFaction": {
                            "@id": "/factions/BR",
                            "@type": "Faction",
                            "reference": "BR",
                            "color": "#c32637",
                            "id": "01GE7AC9WY6PK56RADXXD6P1T4",
                            "name": "Bravos"
                        },
                        "name": "Intimidation",
                        "elements": {
                            "MAIN_COST": "2",
                            "RECALL_COST": "2",
                            "OCEAN_POWER": "",
                            "MOUNTAIN_POWER": "",
                            "FOREST_POWER": "",
                            "MAIN_EFFECT": "[[Fugace]]. (Envoyez-moi à la Défausse plutôt qu'en Réserve après résolution de mon effet.)  Renvoyez un Personnage ou Permanent ciblé avec un Coût de Main {4} ou moins dans la main de son propriétaire."
                        },
                        "siblingReference": "BR_28"
                    },
                    "id": "01JM558988HM54FJB28PEF8WXF"
                }
            ],
            "number": 9
        },
        "permanent": {
            "@type": "DeckCards",
            "@id": "/.well-known/genid/a916272cf71ed60a2691",
            "deckUserListCard": [
                {
                    "@type": "DeckUserListCard",
                    "@id": "/.well-known/genid/298ecc49d9b38560747c",
                    "quantity": 2,
                    "card": {
                        "@id": "/cards/ALT_ALIZE_B_BR_43_C",
                        "@type": "Card",
                        "cardType": {
                            "@id": "/card_types/01J1Q7ASAYXTSM3DH772C70PV5",
                            "@type": "CardType",
                            "reference": "EXPEDITION_PERMANENT",
                            "id": "01J1Q7ASAYXTSM3DH772C70PV5",
                            "name": "Permanent d’Expédition"
                        },
                        "rarity": {
                            "@id": "/rarities/COMMON",
                            "@type": "Rarity",
                            "reference": "COMMON",
                            "name": "Commun"
                        },
                        "imagePath": "https://altered-prod-eu.s3.amazonaws.com/Art/ALIZE/CARDS/ALT_ALIZE_B_BR_43/JPG/fr_FR/6303bf08d427162157e64cbade63cc04.jpg",
                        "inMyCollection": 0,
                        "assets": {
                            "WEB": [
                                "https://altered-prod-eu.s3.amazonaws.com/Art/ALIZE/CARDS/ALT_ALIZE_B_BR_43/WEB_45f8342b1460275baf5510f97cf3d031",
                                "https://altered-prod-eu.s3.amazonaws.com/Art/ALIZE/CARDS/ALT_ALIZE_B_BR_43/WEB_88dc4094659aabdee36cdce5e6c6ce0f"
                            ]
                        },
                        "reference": "ALT_ALIZE_B_BR_43_C",
                        "id": "01J1Q4P4S3CD549S9SSC7PCM6K",
                        "familyReference": "BR_43_C",
                        "mainFaction": {
                            "@id": "/factions/BR",
                            "@type": "Faction",
                            "reference": "BR",
                            "color": "#c32637",
                            "id": "01GE7AC9WY6PK56RADXXD6P1T4",
                            "name": "Bravos"
                        },
                        "name": "Lait d'Arcolano",
                        "elements": {
                            "MAIN_COST": "1",
                            "RECALL_COST": "1",
                            "MAIN_EFFECT": "Lorsqu'un Personnage rejoint mon Expédition — Il gagne 1 boost et [[Fugace]]. (S'il devait être envoyé en Réserve, défaussez-le à la place.)"
                        },
                        "siblingReference": "BR_43"
                    },
                    "id": "01JM559BZY71J4S0R12GR2M7ZF"
                },
                {
                    "@type": "DeckUserListCard",
                    "@id": "/.well-known/genid/b9469e90144dc32d4bcb",
                    "quantity": 3,
                    "card": {
                        "@id": "/cards/ALT_COREKS_B_MU_30_R2",
                        "@type": "Card",
                        "cardType": {
                            "@id": "/card_types/01GE7AC9X78DXSNKNB15KCF69Z",
                            "@type": "CardType",
                            "reference": "PERMANENT",
                            "id": "01GE7AC9X78DXSNKNB15KCF69Z",
                            "name": "Permanent"
                        },
                        "rarity": {
                            "@id": "/rarities/RARE",
                            "@type": "Rarity",
                            "reference": "RARE",
                            "name": "Rare"
                        },
                        "imagePath": "https://altered-prod-eu.s3.amazonaws.com/Art/COREKS/CARDS/ALT_CORE_B_MU_30/JPG/fr_FR/97f966b36b5d342fc0b8818aa2e4f524.jpg",
                        "inMyCollection": 0,
                        "assets": {
                            "WEB": [
                                "https://altered-prod-eu.s3.amazonaws.com/Art/CORE/CARDS/ALT_CORE_B_MU_30/WEB_b727e511c9933fd15eb0f248038ce4f1",
                                "https://altered-prod-eu.s3.amazonaws.com/Art/CORE/CARDS/ALT_CORE_B_MU_30/WEB_cd61c302b8e1d3d3dbc53ccc0701e68f"
                            ]
                        },
                        "reference": "ALT_COREKS_B_MU_30_R2",
                        "id": "01HN5TXRT8V61V1Y38P3KYW6NA",
                        "familyReference": "MU_30_R2",
                        "mainFaction": {
                            "@id": "/factions/BR",
                            "@type": "Faction",
                            "reference": "BR",
                            "color": "#c32637",
                            "id": "01GE7AC9WY6PK56RADXXD6P1T4",
                            "name": "Bravos"
                        },
                        "name": "Le Fuseau, Bastion Muna",
                        "elements": {
                            "MAIN_COST": "3",
                            "RECALL_COST": "3",
                            "OCEAN_POWER": "",
                            "MOUNTAIN_POWER": "",
                            "FOREST_POWER": "",
                            "MAIN_EFFECT": "Les Personnages que vous contrôlez sont [Coriaces 2]. (Les adversaires doivent payer {2} pour les cibler. Les cartes en Réserve ne sont pas contrôlées.)"
                        },
                        "siblingReference": "MU_30"
                    },
                    "id": "01JM553MB92Q98FY69EJSSBXAY"
                }
            ],
            "number": 5
        }
    },
    "cardsByRarityData": [
        [
            "Commun",
            21
        ],
        [
            "Rare",
            15
        ],
        [
            "Unique",
            3
        ]
    ],
    "updatedAt": "2025-02-21T22:10:03+00:00",
    "id": "01JM5539HMGADJKSNJYWKMZN09",
    "description": "",
    "legal": true,
    "cardIndexes": {
        "/cards/ALT_COREKS_B_BR_17_U_1328": 1,
        "/cards/ALT_COREKS_B_BR_27_C": 1,
        "/cards/ALT_CORE_B_MU_18_R2": 2,
        "/cards/ALT_COREKS_B_MU_30_R2": 3,
        "/cards/ALT_ALIZE_B_BR_34_C": 3,
        "/cards/ALT_COREKS_B_BR_19_R1": 2,
        "/cards/ALT_COREKS_B_BR_26_R1": 3,
        "/cards/ALT_COREKS_B_LY_09_U_1373": 1,
        "/cards/ALT_COREKS_B_LY_18_U_488": 1,
        "/cards/ALT_COREKS_B_BR_06_R1": 3,
        "/cards/ALT_COREKS_B_BR_08_C": 2,
        "/cards/ALT_COREKS_B_BR_15_C": 2,
        "/cards/ALT_COREKS_B_BR_28_C": 3,
        "/cards/ALT_ALIZE_B_BR_43_C": 2,
        "/cards/ALT_ALIZE_B_BR_32_C": 3,
        "/cards/ALT_COREKS_B_BR_29_R1": 2,
        "/cards/ALT_ALIZE_B_BR_35_C": 3,
        "/cards/ALT_ALIZE_B_BR_33_C": 2
    }
}